hmeasure/__init__.py
hmeasure/_version.py
hmeasure/hsource.py
hmeasure-0.1.6.dist-info/LICENSE
hmeasure-0.1.6.dist-info/METADATA
hmeasure-0.1.6.dist-info/WHEEL
hmeasure-0.1.6.dist-info/top_level.txt
hmeasure-0.1.6.dist-info/RECORD
