Metadata-Version: 2.1
Name: hmeasure
Version: 0.1.6
Summary: H-Measure Classification Metric
Home-page: https://github.com/ldanov/pypkg_hmeasure
Author: Lyubomir Danov
License: UNKNOWN
Platform: UNKNOWN
Requires-Dist: numpy (>=1.16.1)
Requires-Dist: scikit-learn (>=0.21.1)
Requires-Dist: scipy (>=1.2.1)
